kqlmagic_kernel/__init__.py
kqlmagic_kernel/__main__.py
kqlmagic_kernel/_version.py
kqlmagic_kernel/check.py
kqlmagic_kernel/install.py
kqlmagic_kernel/kernel.py
kqlmagic_kernel/spec/kernel.json
kqlmagic_kernel/spec/images/logo-32x32.png
kqlmagic_kernel/spec/images/logo-64x64.png
kqlmagic_kernel-0.1.0.data/data/share/jupyter/kernels/kqlmagic/kernel.json
kqlmagic_kernel-0.1.0.dist-info/LICENSE.txt
kqlmagic_kernel-0.1.0.dist-info/METADATA
kqlmagic_kernel-0.1.0.dist-info/WHEEL
kqlmagic_kernel-0.1.0.dist-info/top_level.txt
kqlmagic_kernel-0.1.0.dist-info/RECORD
