Metadata-Version: 2.1
Name: kqlmagic-kernel
Version: 0.1.0
Summary: 'A Jupyter kernel for Kqlmagic.'
Home-page: https://github.com/Microsoft/jupyter-Kqlmagic-Kernel
Author: 'Michael Binshtock'
Author-email: michabin@microsoft.com
License: MIT
Platform: UNKNOWN
Classifier: Intended Audience :: Developers
Classifier: Intended Audience :: System Administrators
Classifier: Intended Audience :: Customer Service
Classifier: Intended Audience :: Information Technology
Classifier: Intended Audience :: Science/Research
Classifier: Environment :: Console
Classifier: License :: OSI Approved :: MIT License
Classifier: Natural Language :: English
Classifier: Topic :: Database
Classifier: Topic :: Database :: Front-Ends
Classifier: Framework :: IPython
Classifier: Framework :: Jupyter
Classifier: Operating System :: OS Independent
Classifier: Programming Language :: Python :: 3.6
Classifier: Programming Language :: Python :: 3.7
Classifier: Programming Language :: Python :: 3.8
Classifier: Programming Language :: Python :: 3.9
Classifier: Programming Language :: Python :: 3.10
Classifier: Programming Language :: Python :: 3 :: Only
Requires-Python: >=3.6
License-File: LICENSE.txt
Requires-Dist: kqlmagic (>=0.1.114)
Requires-Dist: jupyter-client (>=4.3.0)
Requires-Dist: ipykernel
Provides-Extra: test
Requires-Dist: pytest ; extra == 'test'
Requires-Dist: nbconvert ; extra == 'test'
Requires-Dist: jupyter-kernel-test ; extra == 'test'
